singularity_pipeline/__init__.py
singularity_pipeline/__main__.py
singularity_pipeline/constants.py
singularity_pipeline/eprint.py
singularity_pipeline/pipeline.py
singularity_pipeline/templates.py
singularity_pipeline-0.2.1.dist-info/METADATA
singularity_pipeline-0.2.1.dist-info/RECORD
singularity_pipeline-0.2.1.dist-info/WHEEL
singularity_pipeline-0.2.1.dist-info/entry_points.txt
singularity_pipeline-0.2.1.dist-info/top_level.txt
